mondo_fs-0.1.2.dist-info/DESCRIPTION.rst
mondo_fs-0.1.2.dist-info/METADATA
mondo_fs-0.1.2.dist-info/RECORD
mondo_fs-0.1.2.dist-info/WHEEL
mondo_fs-0.1.2.dist-info/entry_points.txt
mondo_fs-0.1.2.dist-info/metadata.json
mondo_fs-0.1.2.dist-info/top_level.txt
mondofs/__init__.py
mondofs/__main__.py
mondofs/decorators.py
mondofs/diazed.py
mondofs/mondo.py
